[
  {
    "type": "event",
    "name": "DataSetRailsCreated",
    "inputs": [
      { "name": "dataSetId", "type": "uint256", "indexed": true, "internalType": "uint256" },
      { "name": "pdpRailId", "type": "uint256", "indexed": false, "internalType": "uint256" },
      { "name": "cacheMissRailId", "type": "uint256", "indexed": false, "internalType": "uint256" },
      { "name": "cdnRailId", "type": "uint256", "indexed": false, "internalType": "uint256" },
      { "name": "payer", "type": "address", "indexed": false, "internalType": "address" },
      { "name": "payee", "type": "address", "indexed": false, "internalType": "address" },
      { "name": "withCDN", "type": "bool", "indexed": false, "internalType": "bool" }
    ],
    "anonymous": false
  },
  {
    "type": "event",
    "name": "RailRateUpdated",
    "inputs": [
      { "name": "dataSetId", "type": "uint256", "indexed": true, "internalType": "uint256" },
      { "name": "railId", "type": "uint256", "indexed": false, "internalType": "uint256" },
      { "name": "newRate", "type": "uint256", "indexed": false, "internalType": "uint256" }
    ],
    "anonymous": false
  },
  {
    "type": "event",
    "name": "FaultRecord",
    "inputs": [
      { "name": "dataSetId", "type": "uint256", "indexed": true, "internalType": "uint256" },
      { "name": "periodsFaulted", "type": "uint256", "indexed": false, "internalType": "uint256" },
      { "name": "deadline", "type": "uint256", "indexed": false, "internalType": "uint256" }
    ],
    "anonymous": false
  },
  {
    "type": "event",
    "name": "ProviderApproved",
    "inputs": [
      { "name": "provider", "type": "address", "indexed": true, "internalType": "address" },
      { "name": "providerId", "type": "uint256", "indexed": true, "internalType": "uint256" }
    ],
    "anonymous": false
  },
  {
    "type": "event",
    "name": "ProviderRegistered",
    "inputs": [
      { "name": "provider", "type": "address", "indexed": true, "internalType": "address" },
      { "name": "serviceURL", "type": "string", "indexed": false, "internalType": "string" },
      { "name": "peerId", "type": "bytes", "indexed": false, "internalType": "bytes" }
    ],
    "anonymous": false
  },
  {
    "type": "event",
    "name": "ProviderRejected",
    "inputs": [{ "name": "provider", "type": "address", "indexed": true, "internalType": "address" }],
    "anonymous": false
  },
  {
    "type": "event",
    "name": "ProviderRemoved",
    "inputs": [
      { "name": "provider", "type": "address", "indexed": true, "internalType": "address" },
      { "name": "providerId", "type": "uint256", "indexed": true, "internalType": "uint256" }
    ],
    "anonymous": false
  }
]
